<?xml version="1.0" encoding="utf-8" ?>
<dwsync>
<file name="EdwardianScrITC-Bold.woff" server="hunk-o-mania.com" local="133693403454360249" remote="133662073200000000" Dst="2" />
<file name="EdwardianScrITC-Bold.woff2" server="hunk-o-mania.com" local="133693403455420251" remote="133662073200000000" Dst="2" />
<file name="EurostileNextLTPro-SmBd.woff" server="hunk-o-mania.com" local="133693403457380247" remote="133662073200000000" Dst="2" />
<file name="EurostileNextLTPro-SmBd.woff2" server="hunk-o-mania.com" local="133693403466150251" remote="133662073200000000" Dst="2" />
<file name="TacticSans-Bld.woff" server="hunk-o-mania.com" local="133693403470160264" remote="133661105400000000" Dst="2" />
<file name="TacticSans-Bld.woff2" server="hunk-o-mania.com" local="133693403474900249" remote="133661105400000000" Dst="2" />
<file name="TacticSans-Med.woff" server="hunk-o-mania.com" local="133693403479660251" remote="133661105400000000" Dst="2" />
<file name="TacticSans-Med.woff2" server="hunk-o-mania.com" local="133693403483900248" remote="133661105400000000" Dst="2" />
<file name="TacticSans-Reg.woff" server="hunk-o-mania.com" local="133693403488600248" remote="133661105400000000" Dst="2" />
<file name="TacticSans-Reg.woff2" server="hunk-o-mania.com" local="133693403493010248" remote="133661105400000000" Dst="2" />
<file name="fa-brands-400.ttf" server="hunk-o-mania.com" local="133693403506880252" remote="133661105400000000" Dst="2" />
<file name="fa-brands-400.woff2" server="hunk-o-mania.com" local="133693403507870247" remote="133661105400000000" Dst="2" />
<file name="fa-regular-400.ttf" server="hunk-o-mania.com" local="133693403510010248" remote="133661105400000000" Dst="2" />
<file name="fa-regular-400.woff2" server="hunk-o-mania.com" local="133693403519390247" remote="133661105400000000" Dst="2" />
<file name="fa-solid-900.woff2" server="hunk-o-mania.com" local="133693403535700259" remote="133661105400000000" Dst="2" />
<file name="fa-solid-900.ttf" server="hunk-o-mania.com" local="133693403538450247" remote="133661105400000000" Dst="2" />
<file name="fa-v4compatibility.woff2" server="hunk-o-mania.com" local="133693403543900247" remote="133661105400000000" Dst="2" />
<file name="parsi-bold.woff" server="hunk-o-mania.com" local="133693403549640251" remote="133669789200000000" Dst="2" />
<file name="parsi-bold.woff2" server="hunk-o-mania.com" local="133693403558300247" remote="133669789200000000" Dst="2" />
<file name="parsi-regular.woff" server="hunk-o-mania.com" local="133693403561430246" remote="133669789200000000" Dst="2" />
<file name="parsi-regular.woff2" server="hunk-o-mania.com" local="133693403570280247" remote="133669789200000000" Dst="2" />
<file name="stafford-serial-heavy.woff" server="hunk-o-mania.com" local="133693403573660245" remote="133670665200000000" Dst="2" />
<file name="stafford-serial-heavy.woff2" server="hunk-o-mania.com" local="133693403581590246" remote="133670665200000000" Dst="2" />
<file name="fa-v4compatibility.ttf" server="hunk-o-mania.com" local="133693406478667182" remote="133661105400000000" Dst="2" />
</dwsync>